{
  "version": "stage3_mock_v1",
  "city": "西安",
  "dataType": "activity_pois",
  "note": "Mock 活动 POI。名称借鉴西安本地儿童乐园、商场活动、文旅展览和 citywalk 命名风格；价格、营业、排队和余票均为模拟。",
  "activities": [
    {
      "id": "act_xa_001",
      "name": "稚趣星球Mini乐园(MOMOPARK店)",
      "areaId": "area_xa_xiaozhai",
      "category": "parent_child_playground",
      "tags": ["亲子", "室内", "儿童友好", "少走路", "商场"],
      "openHours": { "weekday": "10:00-20:00", "weekend": "09:30-21:00" },
      "suggestedDurationMinutes": 90,
      "pricePerPerson": 98,
      "ageMin": 2,
      "ageMax": 10,
      "indoorOutdoor": "indoor",
      "baseRating": 4.6,
      "mockBasis": "参考西安 MOMOPARK 儿童乐园命名风格微调"
    },
    {
      "id": "act_xa_002",
      "name": "卡通尼成长乐园(熙地港店)",
      "areaId": "area_xa_xingzheng",
      "category": "parent_child_playground",
      "tags": ["亲子", "室内", "儿童友好", "电玩", "商场"],
      "openHours": { "weekday": "10:00-21:00", "weekend": "10:00-21:30" },
      "suggestedDurationMinutes": 100,
      "pricePerPerson": 88,
      "ageMin": 3,
      "ageMax": 12,
      "indoorOutdoor": "indoor",
      "baseRating": 4.5,
      "mockBasis": "参考熙地港儿童娱乐业态命名风格微调"
    },
    {
      "id": "act_xa_003",
      "name": "POPOME+探索乐园(万象天地店)",
      "areaId": "area_xa_gaoxin",
      "category": "parent_child_playground",
      "tags": ["亲子", "室内", "益智", "儿童友好", "商场"],
      "openHours": { "weekday": "10:00-20:30", "weekend": "10:00-21:30" },
      "suggestedDurationMinutes": 90,
      "pricePerPerson": 118,
      "ageMin": 3,
      "ageMax": 9,
      "indoorOutdoor": "indoor",
      "baseRating": 4.7,
      "mockBasis": "参考 POPOME+ 益智乐园命名风格微调"
    },
    {
      "id": "act_xa_004",
      "name": "多奇妙亲子空间(曲江大悦城店)",
      "areaId": "area_xa_qujiang",
      "category": "parent_child_playground",
      "tags": ["亲子", "室内", "儿童友好", "拍照", "商场"],
      "openHours": { "weekday": "10:00-20:30", "weekend": "09:30-21:30" },
      "suggestedDurationMinutes": 100,
      "pricePerPerson": 128,
      "ageMin": 2,
      "ageMax": 8,
      "indoorOutdoor": "indoor",
      "baseRating": 4.6,
      "mockBasis": "参考多奇妙乐园类亲子品牌命名风格微调"
    },
    {
      "id": "act_xa_005",
      "name": "赛格云顶水族体验馆(小寨店)",
      "areaId": "area_xa_xiaozhai",
      "category": "aquarium_experience",
      "tags": ["亲子", "室内", "拍照", "轻松", "科普"],
      "openHours": { "weekday": "10:00-20:00", "weekend": "10:00-21:00" },
      "suggestedDurationMinutes": 75,
      "pricePerPerson": 68,
      "ageMin": 3,
      "ageMax": 15,
      "indoorOutdoor": "indoor",
      "baseRating": 4.4,
      "mockBasis": "参考小寨商场型体验馆命名风格微调"
    },
    {
      "id": "act_xa_006",
      "name": "曲江艺想展览馆(大悦城店)",
      "areaId": "area_xa_qujiang",
      "category": "exhibition",
      "tags": ["展览", "拍照", "室内", "约会", "安静"],
      "openHours": { "weekday": "11:00-20:30", "weekend": "10:30-21:30" },
      "suggestedDurationMinutes": 80,
      "pricePerPerson": 78,
      "ageMin": 8,
      "ageMax": 99,
      "indoorOutdoor": "indoor",
      "baseRating": 4.5,
      "mockBasis": "参考曲江展览和商场快闪命名风格微调"
    },
    {
      "id": "act_xa_007",
      "name": "大唐夜色光影馆(不夜城店)",
      "areaId": "area_xa_qujiang",
      "category": "photo_spot",
      "tags": ["拍照", "夜游", "约会", "游客密集", "氛围"],
      "openHours": { "weekday": "15:00-22:30", "weekend": "14:00-23:00" },
      "suggestedDurationMinutes": 70,
      "pricePerPerson": 88,
      "ageMin": 6,
      "ageMax": 99,
      "indoorOutdoor": "mixed",
      "baseRating": 4.4,
      "mockBasis": "参考大唐不夜城夜游和光影体验命名风格微调"
    },
    {
      "id": "act_xa_008",
      "name": "城墙里光影展厅(南门店)",
      "areaId": "area_xa_zhonglou",
      "category": "exhibition",
      "tags": ["展览", "拍照", "历史", "约会", "室内"],
      "openHours": { "weekday": "10:30-20:00", "weekend": "10:00-21:00" },
      "suggestedDurationMinutes": 60,
      "pricePerPerson": 58,
      "ageMin": 7,
      "ageMax": 99,
      "indoorOutdoor": "indoor",
      "baseRating": 4.3,
      "mockBasis": "参考西安城墙和南门片区文旅命名风格微调"
    },
    {
      "id": "act_xa_009",
      "name": "唐潮手作工坊(大唐不夜城店)",
      "areaId": "area_xa_qujiang",
      "category": "handcraft",
      "tags": ["手作", "亲子", "约会", "室内", "安静"],
      "openHours": { "weekday": "11:00-20:30", "weekend": "10:30-21:30" },
      "suggestedDurationMinutes": 90,
      "pricePerPerson": 108,
      "ageMin": 6,
      "ageMax": 99,
      "indoorOutdoor": "indoor",
      "baseRating": 4.6,
      "mockBasis": "参考西安唐风文创体验业态命名风格微调"
    },
    {
      "id": "act_xa_010",
      "name": "大明宫轻游营地(龙首原店)",
      "areaId": "area_xa_daminggong",
      "category": "park_light_walk",
      "tags": ["户外", "亲子", "低预算", "少排队", "空间开阔"],
      "openHours": { "weekday": "09:00-19:00", "weekend": "08:30-20:00" },
      "suggestedDurationMinutes": 80,
      "pricePerPerson": 20,
      "ageMin": 3,
      "ageMax": 99,
      "indoorOutdoor": "outdoor",
      "baseRating": 4.2,
      "mockBasis": "参考大明宫遗址公园周边轻活动场景微调"
    },
    {
      "id": "act_xa_011",
      "name": "北院门食光Citywalk(钟楼店)",
      "areaId": "area_xa_zhonglou",
      "category": "citywalk",
      "tags": ["citywalk", "小吃", "朋友", "夜游", "热闹"],
      "openHours": { "weekday": "15:00-22:30", "weekend": "14:00-23:00" },
      "suggestedDurationMinutes": 90,
      "pricePerPerson": 0,
      "ageMin": 10,
      "ageMax": 99,
      "indoorOutdoor": "outdoor",
      "baseRating": 4.1,
      "mockBasis": "参考钟楼-回民街游客型 citywalk 命名风格微调"
    },
    {
      "id": "act_xa_012",
      "name": "兴善寺东街书房(小寨店)",
      "areaId": "area_xa_xiaozhai",
      "category": "bookstore_cafe",
      "tags": ["安静", "轻松", "室内", "约会", "少走路"],
      "openHours": { "weekday": "10:00-21:00", "weekend": "10:00-21:30" },
      "suggestedDurationMinutes": 60,
      "pricePerPerson": 35,
      "ageMin": 6,
      "ageMax": 99,
      "indoorOutdoor": "indoor",
      "baseRating": 4.3,
      "mockBasis": "参考小寨周边书店、咖啡复合空间命名风格微调"
    },
    {
      "id": "act_xa_013",
      "name": "长安造物手作社(高新店)",
      "areaId": "area_xa_gaoxin",
      "category": "handcraft",
      "tags": ["手作", "安静", "室内", "约会", "朋友"],
      "openHours": { "weekday": "12:00-21:00", "weekend": "10:30-21:30" },
      "suggestedDurationMinutes": 100,
      "pricePerPerson": 138,
      "ageMin": 12,
      "ageMax": 99,
      "indoorOutdoor": "indoor",
      "baseRating": 4.7,
      "mockBasis": "参考高新文创体验和手作店命名风格微调"
    },
    {
      "id": "act_xa_014",
      "name": "汉唐小剧场(钟楼店)",
      "areaId": "area_xa_zhonglou",
      "category": "performance",
      "tags": ["演出", "室内", "历史", "约会", "朋友"],
      "openHours": { "weekday": "14:00-22:00", "weekend": "13:00-22:30" },
      "suggestedDurationMinutes": 75,
      "pricePerPerson": 168,
      "ageMin": 8,
      "ageMax": 99,
      "indoorOutdoor": "indoor",
      "baseRating": 4.5,
      "mockBasis": "参考钟楼文旅小剧场和沉浸演艺命名风格微调"
    },
    {
      "id": "act_xa_015",
      "name": "大明宫风筝草坪(遗址公园店)",
      "areaId": "area_xa_daminggong",
      "category": "park_light_walk",
      "tags": ["户外", "亲子", "低预算", "少排队", "轻松"],
      "openHours": { "weekday": "09:00-18:30", "weekend": "08:30-19:30" },
      "suggestedDurationMinutes": 70,
      "pricePerPerson": 15,
      "ageMin": 4,
      "ageMax": 99,
      "indoorOutdoor": "outdoor",
      "baseRating": 4.1,
      "mockBasis": "参考大明宫公园型亲子户外活动命名风格微调"
    },
    {
      "id": "act_xa_016",
      "name": "秦岭自然课堂(高新亲子中心)",
      "areaId": "area_xa_gaoxin",
      "category": "science_workshop",
      "tags": ["亲子", "科普", "室内", "安静", "儿童友好"],
      "openHours": { "weekday": "13:00-19:00", "weekend": "10:00-20:00" },
      "suggestedDurationMinutes": 90,
      "pricePerPerson": 158,
      "ageMin": 6,
      "ageMax": 12,
      "indoorOutdoor": "indoor",
      "baseRating": 4.6,
      "mockBasis": "参考西安自然教育和亲子科普课程命名风格微调"
    }
  ]
}
