{
  "version": "stage3_mock_v1",
  "city": "西安",
  "dataType": "restaurant_pois",
  "note": "Mock 餐厅 POI。名称借鉴西安本地餐饮、新消费品牌和商圈门店命名风格；营业、价格、预约、排队为模拟。",
  "restaurants": [
    {
      "id": "res_xa_001",
      "name": "青禾沙拉实验室(小寨店)",
      "areaId": "area_xa_xiaozhai",
      "cuisine": "light_food",
      "tags": ["低脂", "清淡", "沙拉", "可预约", "少油"],
      "openHours": { "weekday": "10:30-21:00", "weekend": "10:30-21:30" },
      "avgPricePerPerson": 62,
      "childFriendly": false,
      "lowFatOptions": true,
      "reservable": true,
      "baseRating": 4.4,
      "mockBasis": "参考西安小寨轻食、沙拉门店命名风格微调"
    },
    {
      "id": "res_xa_002",
      "name": "山有之Cafe&Meal(小寨店)",
      "areaId": "area_xa_xiaozhai",
      "cuisine": "cafe_meal",
      "tags": ["咖啡", "简餐", "拍照", "约会", "安静"],
      "openHours": { "weekday": "10:00-21:30", "weekend": "10:00-22:00" },
      "avgPricePerPerson": 88,
      "childFriendly": false,
      "lowFatOptions": true,
      "reservable": true,
      "baseRating": 4.6,
      "mockBasis": "参考小寨 cafe&meal 类门店命名风格微调"
    },
    {
      "id": "res_xa_003",
      "name": "悦蔬轻食Bistro(高新大都荟店)",
      "areaId": "area_xa_gaoxin",
      "cuisine": "light_food",
      "tags": ["低脂", "清淡", "可预约", "约会", "白领"],
      "openHours": { "weekday": "11:00-21:30", "weekend": "10:30-22:00" },
      "avgPricePerPerson": 78,
      "childFriendly": false,
      "lowFatOptions": true,
      "reservable": true,
      "baseRating": 4.5,
      "mockBasis": "参考高新轻食和简餐门店命名风格微调"
    },
    {
      "id": "res_xa_004",
      "name": "Mellow Bowl轻食(高新店)",
      "areaId": "area_xa_gaoxin",
      "cuisine": "light_food",
      "tags": ["低脂", "沙拉", "轻食", "安静", "少油"],
      "openHours": { "weekday": "10:30-20:30", "weekend": "10:30-21:00" },
      "avgPricePerPerson": 72,
      "childFriendly": false,
      "lowFatOptions": true,
      "reservable": false,
      "baseRating": 4.3,
      "mockBasis": "参考轻食碗、沙拉店英文命名风格微调"
    },
    {
      "id": "res_xa_005",
      "name": "小六汤包小馆(熙地港店)",
      "areaId": "area_xa_xingzheng",
      "cuisine": "local_snack",
      "tags": ["陕西小吃", "儿童友好", "家庭", "可预约", "商场"],
      "openHours": { "weekday": "10:30-21:00", "weekend": "10:30-21:30" },
      "avgPricePerPerson": 55,
      "childFriendly": true,
      "lowFatOptions": false,
      "reservable": true,
      "baseRating": 4.4,
      "mockBasis": "参考西安小六饮食、汤包类本土餐饮命名风格微调"
    },
    {
      "id": "res_xa_006",
      "name": "长安小牌档(赛格店)",
      "areaId": "area_xa_xiaozhai",
      "cuisine": "shaanxi_cuisine",
      "tags": ["陕菜", "本地特色", "家庭", "游客", "热闹"],
      "openHours": { "weekday": "11:00-22:00", "weekend": "10:30-22:30" },
      "avgPricePerPerson": 86,
      "childFriendly": true,
      "lowFatOptions": false,
      "reservable": true,
      "baseRating": 4.5,
      "mockBasis": "参考长安大牌档类西安本土餐饮命名风格微调"
    },
    {
      "id": "res_xa_007",
      "name": "陕拾叁冰酪小站(大悦城店)",
      "areaId": "area_xa_qujiang",
      "cuisine": "dessert",
      "tags": ["甜品", "本地特色", "拍照", "轻食", "游客"],
      "openHours": { "weekday": "10:30-22:00", "weekend": "10:30-22:30" },
      "avgPricePerPerson": 38,
      "childFriendly": true,
      "lowFatOptions": false,
      "reservable": false,
      "baseRating": 4.4,
      "mockBasis": "参考陕拾叁等西安本土甜品品牌命名风格微调"
    },
    {
      "id": "res_xa_008",
      "name": "茶话巷长安制茶(大雁塔店)",
      "areaId": "area_xa_qujiang",
      "cuisine": "tea_drink",
      "tags": ["茶饮", "本土品牌感", "拍照", "朋友", "轻松"],
      "openHours": { "weekday": "10:00-22:00", "weekend": "10:00-23:00" },
      "avgPricePerPerson": 24,
      "childFriendly": true,
      "lowFatOptions": true,
      "reservable": false,
      "baseRating": 4.5,
      "mockBasis": "参考茶话弄长安文化茶饮命名风格微调"
    },
    {
      "id": "res_xa_009",
      "name": "北院门清真小食铺(钟楼店)",
      "areaId": "area_xa_zhonglou",
      "cuisine": "local_snack",
      "tags": ["小吃", "清真", "朋友", "游客", "热闹"],
      "openHours": { "weekday": "11:00-23:00", "weekend": "10:30-23:30" },
      "avgPricePerPerson": 48,
      "childFriendly": false,
      "lowFatOptions": false,
      "reservable": false,
      "baseRating": 4.1,
      "mockBasis": "参考北院门、回民街小吃命名风格微调"
    },
    {
      "id": "res_xa_010",
      "name": "马记小炒泡馍馆(回民街店)",
      "areaId": "area_xa_zhonglou",
      "cuisine": "local_snack",
      "tags": ["泡馍", "小吃", "本地特色", "游客", "排队"],
      "openHours": { "weekday": "10:30-22:30", "weekend": "10:00-23:00" },
      "avgPricePerPerson": 58,
      "childFriendly": false,
      "lowFatOptions": false,
      "reservable": false,
      "baseRating": 4.2,
      "mockBasis": "参考西安回民街泡馍、小炒类店铺命名风格微调"
    },
    {
      "id": "res_xa_011",
      "name": "魏小家凉皮铺(小寨店)",
      "areaId": "area_xa_xiaozhai",
      "cuisine": "fast_local",
      "tags": ["凉皮", "肉夹馍", "快餐", "低预算", "儿童可接受"],
      "openHours": { "weekday": "10:00-21:00", "weekend": "10:00-21:30" },
      "avgPricePerPerson": 32,
      "childFriendly": true,
      "lowFatOptions": false,
      "reservable": false,
      "baseRating": 4.0,
      "mockBasis": "参考西安本土快餐、凉皮品牌命名风格微调"
    },
    {
      "id": "res_xa_012",
      "name": "云禾家常菜(曲江大悦城店)",
      "areaId": "area_xa_qujiang",
      "cuisine": "home_style",
      "tags": ["家常菜", "儿童友好", "清淡", "可预约", "家庭"],
      "openHours": { "weekday": "11:00-21:30", "weekend": "10:30-22:00" },
      "avgPricePerPerson": 69,
      "childFriendly": true,
      "lowFatOptions": true,
      "reservable": true,
      "baseRating": 4.4,
      "mockBasis": "参考商场家常菜、家庭聚餐门店命名风格微调"
    },
    {
      "id": "res_xa_013",
      "name": "半糖茶餐厅(大雁塔店)",
      "areaId": "area_xa_qujiang",
      "cuisine": "cantonese_cafe",
      "tags": ["茶餐厅", "约会", "可预约", "拍照", "朋友"],
      "openHours": { "weekday": "11:00-22:00", "weekend": "10:30-22:30" },
      "avgPricePerPerson": 92,
      "childFriendly": false,
      "lowFatOptions": true,
      "reservable": true,
      "baseRating": 4.3,
      "mockBasis": "参考曲江商圈轻正餐、茶餐厅命名风格微调"
    },
    {
      "id": "res_xa_014",
      "name": "唐里小院陕菜(大明宫店)",
      "areaId": "area_xa_daminggong",
      "cuisine": "shaanxi_cuisine",
      "tags": ["陕菜", "家庭", "可预约", "空间宽敞", "儿童友好"],
      "openHours": { "weekday": "11:00-21:00", "weekend": "10:30-21:30" },
      "avgPricePerPerson": 76,
      "childFriendly": true,
      "lowFatOptions": false,
      "reservable": true,
      "baseRating": 4.2,
      "mockBasis": "参考大明宫周边院落式陕菜命名风格微调"
    },
    {
      "id": "res_xa_015",
      "name": "安小野烤肉社(钟楼店)",
      "areaId": "area_xa_zhonglou",
      "cuisine": "bbq",
      "tags": ["烤肉", "朋友", "热闹", "夜间", "排队"],
      "openHours": { "weekday": "17:00-01:00", "weekend": "16:30-01:30" },
      "avgPricePerPerson": 118,
      "childFriendly": false,
      "lowFatOptions": false,
      "reservable": true,
      "baseRating": 4.4,
      "mockBasis": "参考西安夜间聚餐、烤肉社类命名风格微调"
    },
    {
      "id": "res_xa_016",
      "name": "西市里茶食馆(高新店)",
      "areaId": "area_xa_gaoxin",
      "cuisine": "tea_meal",
      "tags": ["安静", "可预约", "茶食", "约会", "朋友聊天"],
      "openHours": { "weekday": "11:00-22:00", "weekend": "10:30-22:30" },
      "avgPricePerPerson": 96,
      "childFriendly": false,
      "lowFatOptions": true,
      "reservable": true,
      "baseRating": 4.6,
      "mockBasis": "参考西安文化茶食、安静约会餐厅命名风格微调"
    },
    {
      "id": "res_xa_017",
      "name": "关中巷子biangbiang面(龙首原店)",
      "areaId": "area_xa_daminggong",
      "cuisine": "noodle",
      "tags": ["面食", "低预算", "本地特色", "家庭", "快餐"],
      "openHours": { "weekday": "10:30-21:00", "weekend": "10:30-21:30" },
      "avgPricePerPerson": 36,
      "childFriendly": true,
      "lowFatOptions": false,
      "reservable": false,
      "baseRating": 4.1,
      "mockBasis": "参考西安面食、小吃连锁命名风格微调"
    },
    {
      "id": "res_xa_018",
      "name": "松间咖啡与简餐(熙地港店)",
      "areaId": "area_xa_xingzheng",
      "cuisine": "cafe_meal",
      "tags": ["咖啡", "简餐", "安静", "可预约", "朋友聊天"],
      "openHours": { "weekday": "10:00-21:30", "weekend": "10:00-22:00" },
      "avgPricePerPerson": 68,
      "childFriendly": true,
      "lowFatOptions": true,
      "reservable": true,
      "baseRating": 4.4,
      "mockBasis": "参考熙地港商场咖啡简餐命名风格微调"
    }
  ]
}
